nimbus_lib/__init__.py
nimbus_lib/config.py
nimbus_lib/configs.py
nimbus_lib/nimbus_stack.py
nimbus_lib/stacks/__init__.py
nimbus_lib/stacks/fargate_stack.py
nimbus_lib-0.1.0.dist-info/METADATA
nimbus_lib-0.1.0.dist-info/WHEEL
nimbus_lib-0.1.0.dist-info/licenses/LICENSE
nimbus_lib-0.1.0.dist-info/RECORD
