Metadata-Version: 2.1
Name: nimbus-lib
Version: 0.1.0
Summary: Library wrapping AWS CDK primitives in a useful way.
Author-email: Matt White <mail@matt-w.net>
License-File: LICENSE
Requires-Python: >=3.10
Requires-Dist: aws-cdk-lib~=2.84.0
Requires-Dist: constructs~=10.2.52
Requires-Dist: pydantic~=1.10.9
Requires-Dist: python-dotenv~=1.0.0
Requires-Dist: structlog~=23.1.0
